.mypy_cache/3.11/acli/clients/__init__.data.json
.mypy_cache/3.11/acli/clients/__init__.meta.json
.mypy_cache/3.11/acli/clients/agile.data.json
.mypy_cache/3.11/acli/clients/agile.meta.json
.mypy_cache/3.11/acli/clients/agilecloud.data.json
.mypy_cache/3.11/acli/clients/agilecloud.meta.json
.mypy_cache/3.11/acli/clients/bitbucket.data.json
.mypy_cache/3.11/acli/clients/bitbucket.meta.json
.mypy_cache/3.11/acli/clients/bitbucketcloud.data.json
.mypy_cache/3.11/acli/clients/bitbucketcloud.meta.json
.mypy_cache/3.11/acli/clients/cli.data.json
.mypy_cache/3.11/acli/clients/cli.meta.json
.mypy_cache/3.11/acli/clients/confluence.data.json
.mypy_cache/3.11/acli/clients/confluence.meta.json
.mypy_cache/3.11/acli/clients/confluencecloud.data.json
.mypy_cache/3.11/acli/clients/confluencecloud.meta.json
.mypy_cache/3.11/acli/clients/csv.data.json
.mypy_cache/3.11/acli/clients/csv.meta.json
.mypy_cache/3.11/acli/clients/jira.data.json
.mypy_cache/3.11/acli/clients/jira.meta.json
.mypy_cache/3.11/acli/clients/jiracloud.data.json
.mypy_cache/3.11/acli/clients/jiracloud.meta.json
.mypy_cache/3.11/acli/clients/marketplace.data.json
.mypy_cache/3.11/acli/clients/marketplace.meta.json
.mypy_cache/3.11/acli/clients/monday.data.json
.mypy_cache/3.11/acli/clients/monday.meta.json
.mypy_cache/3.11/acli/clients/options.data.json
.mypy_cache/3.11/acli/clients/options.meta.json
.mypy_cache/3.11/acli/clients/slack.data.json
.mypy_cache/3.11/acli/clients/slack.meta.json
.mypy_cache/3.11/acli/clients/system.data.json
.mypy_cache/3.11/acli/clients/system.meta.json
.mypy_cache/3.11/acli/clients/upm.data.json
.mypy_cache/3.11/acli/clients/upm.meta.json
.mypy_cache/3.11/acli/clients/upmcloud.data.json
.mypy_cache/3.11/acli/clients/upmcloud.meta.json
.mypy_cache/3.11/acli/clients/web.data.json
.mypy_cache/3.11/acli/clients/web.meta.json
acli/__init__.py
acli/base/__init__.py
acli/base/args.py
acli/base/spec.py
acli/clients/__init__.py
acli/clients/agile.py
acli/clients/agilecloud.py
py_acli-0.1.1.dist-info/METADATA
py_acli-0.1.1.dist-info/WHEEL
py_acli-0.1.1.dist-info/RECORD
